Workbook
Name inp_area_ft2: 'Inputs'!$B$2
Name inp_cooling_tons: 'Inputs'!$B$3
Name inp_fan_hp: 'Inputs'!$B$4
Name inp_elec_rate: 'Inputs'!$B$5
Name inp_gas_rate: 'Inputs'!$B$6
Name inp_discount: 'Inputs'!$B$7
Name inp_escalation: 'Inputs'!$B$8
Name inp_life_years: 'Inputs'!$B$9
Name inp_usd_per_ft2: 'Inputs'!$B$10
Name inp_coverage: 'Inputs'!$B$11

Sheet Cover
A1: WattLab Engineering Notebook
A2: ECM package screening (ESCO bin-method vs EnergyPlus)
A4: Building | B4: BUILDING
A5: Package id | B5: controls_first
A6: Package | B6: 1 · Controls-first (no capital RCx)
A7: Honesty | B7: screening — schedules / sensors / standby+DCV
A8: Generated (UTC) | B8: 2026-07-25T19:56:47Z
A9: Catalog package | B9: no-capital-rcx
A10: n_measures | B10: 7
A11: Guardrail verdict | B11: INVESTIGATE
A12: ESCO docs | B12: https://github.com/bbartling/py-bacnet-stacks-playground/blob/develop/vibe_code_apps_20/docs/ESCO_SPREADSHEET_CALCS.md
A13: Note | B13: Yellow cells on Inputs are engineer-editable. ESCO_Calcs / Compare / ROI use formulas where marked.

Sheet Inputs
A1: parameter | B1: value | C1: unit | D1: notes
A2: area_ft2 | B2: 50000 | C2: ft² | D2: Conditioned floor area
A3: cooling_tons | C3: tons | D3: Optional nameplate
A4: fan_hp | C4: HP | D4: Optional supply fan
A5: elec_rate | B5: 0.12 | C5: $/kWh | D5: Blended electric rate
A6: gas_rate | B6: 0.8 | C6: $/therm | D6: Blended gas rate
A7: discount | B7: 0.05 | C7: fraction | D7: NPV discount rate
A8: escalation | B8: 0.02 | C8: fraction | D8: Utility escalation
A9: life_years | B9: 15 | C9: yr | D9: Measure life
A10: usd_per_ft2 | B10: 3 | C10: $/ft² | D10: Fallback package cost intensity
A11: coverage | B11: 1 | C11: 0–1 | D11: Fraction of floor area receiving ECMs

Sheet ESCO_Calcs
A1: measure_id | B1: savings_kwh | C1: savings_therms | D1: calculators | E1: annual_cost_saved_formula | F1: notes
A2: ECM-AHU-SCHED-ALIGN | B2: 277595.8 | C2: 5845.4 | E2: =B2*inp_elec_rate+C2*inp_gas_rate | F2: Screening proxy from wattlab.studio.proxies / bench ESCO bins
A3: ECM-OA-DAMPER-REPAIR | B3: 0 | C3: 0 | E3: =B3*inp_elec_rate+C3*inp_gas_rate | F3: Screening proxy from wattlab.studio.proxies / bench ESCO bins
A4: ECM-SENSOR-CRITICAL-REFRESH | B4: 0 | C4: 0 | E4: =B4*inp_elec_rate+C4*inp_gas_rate | F4: Screening proxy from wattlab.studio.proxies / bench ESCO bins
A5: ECM-OCC-STANDBY-DCV | B5: 46111.2 | C5: 5042.8 | D5: oad_unoccupied_closed,dcv_bins | E5: =B5*inp_elec_rate+C5*inp_gas_rate | F5: Screening proxy from wattlab.studio.proxies / bench ESCO bins
A6: ECM-CHILLER-LOCKOUT | B6: 34524.9 | C6: 0 | E6: =B6*inp_elec_rate+C6*inp_gas_rate | F6: Screening proxy from wattlab.studio.proxies / bench ESCO bins
A7: ECM-SENSOR-CALIBRATION | B7: 0 | C7: 0 | E7: =B7*inp_elec_rate+C7*inp_gas_rate | F7: Screening proxy from wattlab.studio.proxies / bench ESCO bins
A8: ECM-RCX-SETPOINT-REVIEW | B8: 277595.8 | C8: 5845.4 | E8: =B8*inp_elec_rate+C8*inp_gas_rate | F8: Screening proxy from wattlab.studio.proxies / bench ESCO bins

Sheet EPlus_Results
A1: measure_id | B1: kwh_saved | C1: therms_saved | D1: peak_kw_delta | E1: source
A2: ECM-AHU-SCHED-ALIGN | E2: E+ not run — ESCO only
A3: ECM-OA-DAMPER-REPAIR | E3: E+ not run — ESCO only
A4: ECM-SENSOR-CRITICAL-REFRESH | E4: E+ not run — ESCO only
A5: ECM-OCC-STANDBY-DCV | E5: E+ not run — ESCO only
A6: ECM-CHILLER-LOCKOUT | E6: E+ not run — ESCO only
A7: ECM-SENSOR-CALIBRATION | E7: E+ not run — ESCO only
A8: ECM-RCX-SETPOINT-REVIEW | E8: E+ not run — ESCO only

Sheet Compare
A1: measure_id | B1: esco_kwh | C1: ep_kwh | D1: delta_kwh | E1: ratio_ep_esco | F1: esco_therms | G1: ep_therms | H1: verdict | I1: light
A2: ECM-AHU-SCHED-ALIGN | B2: =ESCO_Calcs!B2 | C2: =EPlus_Results!B2 | D2: =IF(OR(C2="",C2=0),"",C2-B2) | E2: =IF(OR(B2=0,C2=""),"",C2/B2) | F2: =ESCO_Calcs!C2 | G2: =EPlus_Results!C2 | H2: INSUFFICIENT_EVIDENCE | I2: YELLOW
A3: ECM-OA-DAMPER-REPAIR | B3: =ESCO_Calcs!B3 | C3: =EPlus_Results!B3 | D3: =IF(OR(C3="",C3=0),"",C3-B3) | E3: =IF(OR(B3=0,C3=""),"",C3/B3) | F3: =ESCO_Calcs!C3 | G3: =EPlus_Results!C3 | H3: INSUFFICIENT_EVIDENCE | I3: YELLOW
A4: ECM-SENSOR-CRITICAL-REFRESH | B4: =ESCO_Calcs!B4 | C4: =EPlus_Results!B4 | D4: =IF(OR(C4="",C4=0),"",C4-B4) | E4: =IF(OR(B4=0,C4=""),"",C4/B4) | F4: =ESCO_Calcs!C4 | G4: =EPlus_Results!C4 | H4: INSUFFICIENT_EVIDENCE | I4: YELLOW
A5: ECM-OCC-STANDBY-DCV | B5: =ESCO_Calcs!B5 | C5: =EPlus_Results!B5 | D5: =IF(OR(C5="",C5=0),"",C5-B5) | E5: =IF(OR(B5=0,C5=""),"",C5/B5) | F5: =ESCO_Calcs!C5 | G5: =EPlus_Results!C5 | H5: INSUFFICIENT_EVIDENCE | I5: YELLOW
A6: ECM-CHILLER-LOCKOUT | B6: =ESCO_Calcs!B6 | C6: =EPlus_Results!B6 | D6: =IF(OR(C6="",C6=0),"",C6-B6) | E6: =IF(OR(B6=0,C6=""),"",C6/B6) | F6: =ESCO_Calcs!C6 | G6: =EPlus_Results!C6 | H6: INSUFFICIENT_EVIDENCE | I6: YELLOW
A7: ECM-SENSOR-CALIBRATION | B7: =ESCO_Calcs!B7 | C7: =EPlus_Results!B7 | D7: =IF(OR(C7="",C7=0),"",C7-B7) | E7: =IF(OR(B7=0,C7=""),"",C7/B7) | F7: =ESCO_Calcs!C7 | G7: =EPlus_Results!C7 | H7: INSUFFICIENT_EVIDENCE | I7: YELLOW
A8: ECM-RCX-SETPOINT-REVIEW | B8: =ESCO_Calcs!B8 | C8: =EPlus_Results!B8 | D8: =IF(OR(C8="",C8=0),"",C8-B8) | E8: =IF(OR(B8=0,C8=""),"",C8/B8) | F8: =ESCO_Calcs!C8 | G8: =EPlus_Results!C8 | H8: INSUFFICIENT_EVIDENCE | I8: YELLOW

Sheet ROI_Capital
A1: measure_id | B1: implementation_cost_usd | C1: kwh_saved | D1: therms_saved | E1: annual_cost_saved_usd | F1: simple_payback_years | G1: npv_usd | H1: cost_formula
A2: ECM-AHU-SCHED-ALIGN | B2: 150000 | C2: 277595.8 | D2: 5845.4 | E2: =C2*inp_elec_rate+D2*inp_gas_rate | F2: =IF(E2=0,"",B2/E2) | G2: 296501.59 | H2: =inp_usd_per_ft2*inp_area_ft2*inp_coverage/7
A3: ECM-OA-DAMPER-REPAIR | B3: 150000 | C3: 0 | D3: 0 | E3: =C3*inp_elec_rate+D3*inp_gas_rate | F3: =IF(E3=0,"",B3/E3) | G3: -150000 | H3: =inp_usd_per_ft2*inp_area_ft2*inp_coverage/7
A4: ECM-SENSOR-CRITICAL-REFRESH | B4: 150000 | C4: 0 | D4: 0 | E4: =C4*inp_elec_rate+D4*inp_gas_rate | F4: =IF(E4=0,"",B4/E4) | G4: -150000 | H4: =inp_usd_per_ft2*inp_area_ft2*inp_coverage/7
A5: ECM-OCC-STANDBY-DCV | B5: 150000 | C5: 46111.2 | D5: 5042.8 | E5: =C5*inp_elec_rate+D5*inp_gas_rate | F5: =IF(E5=0,"",B5/E5) | G5: -37544.43 | H5: =inp_usd_per_ft2*inp_area_ft2*inp_coverage/7
A6: ECM-CHILLER-LOCKOUT | B6: 150000 | C6: 34524.9 | D6: 0 | E6: =C6*inp_elec_rate+D6*inp_gas_rate | F6: =IF(E6=0,"",B6/E6) | G6: -101304.1 | H6: =inp_usd_per_ft2*inp_area_ft2*inp_coverage/7
A7: ECM-SENSOR-CALIBRATION | B7: 150000 | C7: 0 | D7: 0 | E7: =C7*inp_elec_rate+D7*inp_gas_rate | F7: =IF(E7=0,"",B7/E7) | G7: -150000 | H7: =inp_usd_per_ft2*inp_area_ft2*inp_coverage/7
A8: ECM-RCX-SETPOINT-REVIEW | B8: 150000 | C8: 277595.8 | D8: 5845.4 | E8: =C8*inp_elec_rate+D8*inp_gas_rate | F8: =IF(E8=0,"",B8/E8) | G8: 296501.59 | H8: =inp_usd_per_ft2*inp_area_ft2*inp_coverage/7
A9: TOTAL | B9: =SUM(B2:B8) | E9: =SUM(E2:E8) | G9: =SUM(G2:G8)

Sheet Guardrails
A1: check | B1: status | C1: detail
A2: overall_verdict | B2: INVESTIGATE | C2: investigate_count=6
A3: baseline_eui_band | B3: skipped | C3: No site EUI provided (load bills first).
A4: savings_fraction | B4: skipped | C4: No baseline consumption provided (load bills first).
A5: measure_cost_band | B5: investigate | C5: ECM-AHU-SCHED-ALIGN: $3.0/building_ft2 is above the 'rcx_tuning' reference band ($0.05-0.5, 2020$, high confidence).
A6: measure_cost_band | B6: investigate | C6: ECM-RCX-SETPOINT-REVIEW: $3.0/building_ft2 is above the 'rcx_tuning' reference band ($0.05-0.5, 2020$, high confidence).
A7: measure_cost_band | B7: ok | C7: ECM-OCC-STANDBY-DCV: $3.0/building_ft2 vs 'minor_hvac_controls' band $1.5-3.5 (2017$).
A8: measure_cost_band | B8: investigate | C8: ECM-CHILLER-LOCKOUT: $3.0/building_ft2 is above the 'rcx_tuning' reference band ($0.05-0.5, 2020$, high confidence).
A9: measure_cost_band | B9: investigate | C9: ECM-OA-DAMPER-REPAIR: $3.0/building_ft2 is above the 'rcx_tuning' reference band ($0.05-0.5, 2020$, high confidence).
A10: measure_cost_band | B10: investigate | C10: ECM-SENSOR-CRITICAL-REFRESH: $3.0/building_ft2 is above the 'rcx_tuning' reference band ($0.05-0.5, 2020$, high confidence).
A11: measure_cost_band | B11: investigate | C11: ECM-SENSOR-CALIBRATION: $3.0/building_ft2 is above the 'rcx_tuning' reference band ($0.05-0.5, 2020$, high confidence).

Sheet Docs
A1: Documentation & calculator map
A3: ESCO spreadsheet calcs (human map) | B3: https://github.com/bbartling/py-bacnet-stacks-playground/blob/develop/vibe_code_apps_20/docs/ESCO_SPREADSHEET_CALCS.md
A4: Python bin calculators | B4: wattlab/bench/esco.py · wattlab/studio/proxies.py
A5: Crosscheck | B5: wattlab/crosscheck.py (~0.5–2× = reasonable)
A6: Finance / NPV | B6: wattlab/finance.py
A7: Catalog package | B7: no-capital-rcx
A8: Measure ids | B8: ECM-AHU-SCHED-ALIGN, ECM-OA-DAMPER-REPAIR, ECM-SENSOR-CRITICAL-REFRESH, ECM-OCC-STANDBY-DCV, ECM-CHILLER-LOCKOUT, ECM-SENSOR-CALIBRATION, ECM-RCX-SETPOINT-REVIEW
A10: Agent CLI | B10: wattlab notebook build --package controls_first --out reports/notebooks/
